nonebot_plugin_mixin/__init__.py
nonebot_plugin_mixin/config.py
nonebot_plugin_mixin-0.2.0.dist-info/LICENSE
nonebot_plugin_mixin-0.2.0.dist-info/METADATA
nonebot_plugin_mixin-0.2.0.dist-info/WHEEL
nonebot_plugin_mixin-0.2.0.dist-info/top_level.txt
nonebot_plugin_mixin-0.2.0.dist-info/RECORD
