Metadata-Version: 2.1
Name: nonebot-plugin-mixin
Version: 0.2.0
Summary: 通过代码或非代码方式外部介入 NoneBot2 插件行为
Author-email: HivertMoZara <worldmozara@163.com>
License: MIT
Project-URL: Homepage, https://github.com/NCBM/nonebot-plugin-mixin
Project-URL: Repository, https://github.com/NCBM/nonebot-plugin-mixin
Requires-Python: >=3.8
License-File: LICENSE
Requires-Dist: nonebot2 >=2.2.0
